my_etl_package/__init__.py
my_etl_package/load_data.py
my_etl_package/read_data.py
my_etl_package/transform_data.py
my_etl_package/write_data.py
my_etl_package/utils/__init__.py
my_etl_package/utils/connect_db.py
my_etl_package/utils/fetch_files.py
my_etl_package-1.0.0.dist-info/LICENSE
my_etl_package-1.0.0.dist-info/METADATA
my_etl_package-1.0.0.dist-info/WHEEL
my_etl_package-1.0.0.dist-info/top_level.txt
my_etl_package-1.0.0.dist-info/RECORD
