Metadata-Version: 2.1
Name: my-etl-package
Version: 1.0.0
Summary: A package for ETL pipeline operations
Author: Khaled Ahmed
Author-email: khhaledahmaad@gmail.com
Classifier: Development Status :: 4 - Beta
Classifier: Environment :: Other Environment
Classifier: Intended Audience :: Developers
Classifier: License :: OSI Approved :: MIT License
Classifier: Operating System :: OS Independent
Classifier: Programming Language :: Python
Classifier: Programming Language :: Python :: 3.10
Classifier: Programming Language :: Python :: 3.11
Classifier: Topic :: Software Development
Classifier: Topic :: Software Development :: Libraries :: Python Modules
Requires-Python: >=3.10
License-File: LICENSE
Requires-Dist: python-dotenv
Requires-Dist: numpy
Requires-Dist: pandas
Requires-Dist: sqlalchemy
Requires-Dist: psycopg2-binary
